devnet_ssh/__init__.py
devnet_ssh/ssh_connect.py
devnet_ssh-1.0.5.dist-info/LICENSE
devnet_ssh-1.0.5.dist-info/METADATA
devnet_ssh-1.0.5.dist-info/WHEEL
devnet_ssh-1.0.5.dist-info/top_level.txt
devnet_ssh-1.0.5.dist-info/RECORD
