Metadata-Version: 2.1
Name: devnet_ssh
Version: 1.0.5
Summary: Fast and simple SSH library for interactive session based on Paramiko
Home-page: https://github.com/jcdaniel14/devnet_ssh.git
Author: Gustavo Santiago
Author-email: jcdaniel14@gmail.com
License: MIT
Download-URL: https://pypi.org/project/devnet_ssh/
Keywords: SSH,SSH Client,Paramiko,Devnet
Platform: UNKNOWN
